subconverter/__init__.py
subconverter/base.py
subconverter/utils.py
subconverter/webvtt.py
subconverter-0.0.2.dist-info/LICENSE
subconverter-0.0.2.dist-info/METADATA
subconverter-0.0.2.dist-info/WHEEL
subconverter-0.0.2.dist-info/top_level.txt
subconverter-0.0.2.dist-info/RECORD
