Metadata-Version: 2.1
Name: subconverter
Version: 0.0.2
Summary: Convert content into different subtitle formats
Home-page: https://github.com/baloda/subconverter
Author: Dharmveer Baloda
Author-email: dharmvrbaloda836@gmail.com
License: UNKNOWN
Project-URL: Bug Tracker, https://github.com/baloda/subconverter/issues
Platform: UNKNOWN
Classifier: Programming Language :: Python :: 3
Classifier: License :: OSI Approved :: MIT License
Classifier: Operating System :: OS Independent
Requires-Python: >=3.6
